counting_package/__init__.py
counting_package/counting.py
counting_package/text.txt
counting_package-0.0.2.dist-info/METADATA
counting_package-0.0.2.dist-info/WHEEL
counting_package-0.0.2.dist-info/licenses/LICENSE
counting_package-0.0.2.dist-info/RECORD
